breadability
tests
